gchangepoint/MST.so
gchangepoint/__init__.py
gchangepoint/gchangepoint.py
gchangepoint/graphutilities.py
gchangepoint/.ipynb_checkpoints/GraphUtilities-checkpoint.py
gchangepoint-0.0.4.dist-info/METADATA
gchangepoint-0.0.4.dist-info/WHEEL
gchangepoint-0.0.4.dist-info/licenses/LICENSE
gchangepoint-0.0.4.dist-info/RECORD
